{
    "id": 98447706,
    "name": "Friend Factory",
    "author": "miamakura",
    "creators": [],
    "verifier": "miamakura",
    "verification": "https://www.youtube.com/watch?v=OSkDmEvKenY",
    "percentToQualify": "100",
    "password": "N/A",
    "records": [
        {
            "user": "mariokirby1703",
            "link": "https://www.youtube.com/watch?v=gC-3yPkmj3w",
            "percent": 100,
            "hz": "01:35:32.716"
        },
        {
            "user": "Adanz9",
            "link": "https://www.youtube.com/watch?v=eo45ncQXm7U",
            "percent": 100,
            "hz": "00:12:32.770"
        },
        {
            "user": "SyncDL",
            "link": "https://www.youtube.com/watch?v=dbH00nCkElU",
            "percent": 100,
            "hz": "00:26:26.925"
        },
        {
            "user": "Colouts",
            "link": "https://www.youtube.com/watch?v=qHTWAg2OAms",
            "percent": 100,
            "hz": "00:21:48.904"
        },
        {
            "user": "ZynTagY_927",
            "link": "https://youtu.be/FyhtjNBZ3iE?si=uuJQwrr1-dHDaiz5",
            "percent": 100,
            "hz": "00:30:54.508"
        },
        {
            "user": "SWB Pro",
            "link": "https://youtu.be/eUXkVbdPYEk?si=F38MzzVVMn4szmIr",
            "percent": 100,
            "hz": "00:32:21.433"
        },
        {
            "user": "Double2",
            "link": "https://www.youtube.com/watch?v=Frg90qktCEE&list=PLMYt0wbSdmakQL-qeI50BW-ESvahup25R&index=9",
            "percent": 100,
            "hz": "00:13:24.966"
        }
    ]
}
