{
    "id": 101647486,
    "name": "Granite",
    "author": "SpikyGMD",
    "creators": [],
    "verifier": "SpikyGMD",
    "verification": "https://www.youtube.com/watch?v=F2BJEA5KjbU",
    "percentToQualify": "100",
    "password": "N/A",
    "records": [
        {
            "user": "Voiddle",
            "link": "https://www.youtube.com/watch?v=71xEHd82KVE",
            "percent": 100,
            "hz": "00:02:35.691"
        },
        {
            "user": "Adanz9",
            "link": "https://www.youtube.com/watch?v=a37s7uRIr08",
            "percent": 100,
            "hz": "00:02:35.691"
        },
        {
            "user": "Colouts",
            "link": "https://www.youtube.com/watch?v=DLV4pwvBrws",
            "percent": 100,
            "hz": "00:02:35.691"
        },
        {
            "user": "IvanCrafter026",
            "link": "https://youtu.be/WjNl3RQ26pM",
            "percent": 100,
            "hz": "00:02:35.691"
        },
        {
            "user": "SyncDL",
            "link": "https://www.youtube.com/watch?v=DS1AsccJ7Y0",
            "percent": 100,
            "hz": "00:02:35.691"
        },
        {
            "user": "Enzo1141",
            "link": "https://youtu.be/rKHZ7BEhweI",
            "percent": 100,
            "hz": "00:02:35.691"
        },
        {
            "user": "ZynTagY_927",
            "link": "https://www.youtube.com/watch?v=YtCDr4dabIY",
            "percent": 100,
            "hz": "00:02:35.691"
        },
        {
            "user": "ZainAhmed",
            "link": "https://www.youtube.com/watch?v=Ke-ImSgp0zY",
            "percent": 100,
            "hz": "00:02:35.691"
        }
    ]
}
