{
    "id": 99170473,
    "name": "Idling Somewhere",
    "author": "Hychie",
    "creators": [],
    "verifier": "Hychie",
    "verification": "https://www.youtube.com/watch?v=Vi5E-tKtShE",
    "percentToQualify": "100",
    "password": "N/A",
    "records": [
        {
            "user": "mariokirby1703",
            "link": "https://www.youtube.com/watch?v=DSLAgAXQ9Qc",
            "percent": 100,
            "hz": "00:01:41.112"
        },
        {
            "user": "Enzo1141",
            "link": "https://www.youtube.com/watch?v=CG7PpdgsdfE",
            "percent": 100,
            "hz": "00:01:12.770"
        },
        {
            "user": "Arouvis",
            "link": "https://youtu.be/-OVMoBYTf3w",
            "percent": 100,
            "hz": "00:02:48.320"
        },
        {
            "user": "IvanCrafter026",
            "link": "https://www.youtube.com/watch?v=65JJaG3LkXU",
            "percent": 100,
            "hz": "00:03:08.900"
        }
    ]
}
