{
    "id": 101298431,
    "name": "Switchscapes",
    "author": "DubbyBall",
    "creators": [],
    "verifier": "DubbyBall",
    "verification": "https://www.youtube.com/watch?v=2xyr-Q3lTOU",
    "percentToQualify": "100",
    "password": "N/A",
    "records": [
        {
            "user": "Voiddle",
            "link": "https://www.youtube.com/watch?v=2Z25JLY2nNA",
            "percent": 100,
            "hz": "01:10:42.737"
        },
        {
            "user": "Archmage7",
            "hz": "00:30:04.879",
            "percent": 100,
            "link": "https://youtu.be/-f0XziTGhBU?si=gEeGJGKYcTigUKHD"
        },
        {
            "user": "SyncDL",
            "hz": "00:18:12.925",
            "percent": 100,
            "link": "https://www.youtube.com/watch?v=z6UGJXDeyzI"
        },
        {
            "user": "mariokirby1703",
            "hz": "00:22:13.916",
            "percent": 100,
            "link": "https://www.youtube.com/watch?v=bmmzNWuVduM"
        },
        {
            "user": "Enzo1141",
            "hz": "00:30:53.887",
            "percent": 100,
            "link": "https://www.youtube.com/watch?v=aWjTiBsC4Mc"
        },
        {
            "user": "Arouvis",
            "link": "https://youtu.be/DGMDIaOoyIo",
            "percent": 100,
            "hz": "00:16:03.987"
        },
        {
            "user": "IvanCrafter026",
            "link": "https://youtu.be/MoZQI0Tmon8",
            "percent": 100,
            "hz": "00:08:47.825"
        }
    ]
}
