{
    "id": 102814497,
    "name": "The Towerverse",
    "author": "16lord",
    "creators": [],
    "verifier": "16lord",
    "verification": "https://www.youtube.com/watch?v=3_QN8vgbFFM",
    "percentToQualify": "100",
    "password": "N/A",
    "records": [
        {
            "user": "mariokirby1703",
            "link": "https://www.youtube.com/watch?v=IeJ99BJBUeA",
            "percent": 100,
            "hz": "00:53:45.146"
        },
        {
            "user": "MrNexis",
            "link": "https://www.youtube.com/watch?v=utGBtjF4Quk",
            "percent": 100,
            "hz": "00:49:08.495"
        },
        {
            "user": "Adanz9",
            "link": "https://www.youtube.com/watch?v=30sK2hNuET4",
            "percent": 100,
            "hz": "00:43:32.333"
        },
        {
            "user": "Voiddle",
            "link": "https://www.youtube.com/watch?v=fuQVXy5S4rQ",
            "percent": 100,
            "hz": "01:16:41.766"
        },
        {
            "user": "Talcticol",
            "link": "https://www.youtube.com/watch?v=16IM-y0VRgY",
            "percent": 100,
            "hz": "01:46:01.125"
        },
        {
            "user": "Archmage7",
            "link": "https://www.youtube.com/watch?v=RDpNqfz_Smg",
            "percent": 100,
            "hz": "01:19:18.483"
        },
        {
            "user": "ZynTagY_927",
            "link": "https://www.youtube.com/watch?v=RDpNqfz_Smg",
            "percent": 100,
            "hz": "01:19:26.800"
        },
        {
            "user": "SyncDL",
            "link": "https://www.youtube.com/watch?v=c2DfWSugQ64",
            "percent": 100,
            "hz": "00:25:00.475"
        },
        {
            "user": "Prometheus",
            "link": "https://www.youtube.com/watch?v=Jl-ZLs2bRhA",
            "percent": 100,
            "hz": "01:43:43.062"
        },
        {
            "user": "Xvelocityy",
            "link": "https://youtu.be/cHgq4UGS8Uo",
            "percent": 100,
            "hz": "01:39:55.137"
        },
        {
            "user": "Arouvis",
            "link": "https://www.youtube.com/watch?v=I4jbvRleCFI",
            "percent": 100,
            "hz": "00:47:18.529"
        },
        {
            "user": "Colouts",
            "link": "https://youtu.be/qKez_ZXff2A?si=Xj6y5hh7qNEIBgxW",
            "percent": 100,
            "hz": "00:49:34.737"
        }
    ]
}